dagorama/__init__.py
dagorama/api/__init__.py
dagorama/api/api_pb2.py
dagorama/api/api_pb2.pyi
dagorama/api/api_pb2_grpc.py
dagorama/api/api_pb2_grpc.pyi
dagorama/cli.py
dagorama/code_signature.py
dagorama/decorators.py
dagorama/definition.py
dagorama/hot_reload.py
dagorama/inspection.py
dagorama/logging.py
dagorama/models/__init__.py
dagorama/models/arguments.py
dagorama/models/promise.py
dagorama/retry.py
dagorama/runner.py
dagorama/serializer.py
dagorama/tests/__init__.py
dagorama/tests/conftest.py
dagorama/tests/test_code_signature.py
dagorama/tests/test_decorators.py
dagorama/tests/test_definition.py
dagorama/tests/test_hot_reload.py
dagorama/tests/test_logging.py
dagorama/tests/test_retry.py
dagorama/tests/test_runner.py
dagorama/tests/test_sample_dag.py
dagorama/tests/test_typecheck.py
dagorama-0.1.10.dist-info/LICENSE
dagorama-0.1.10.dist-info/METADATA
dagorama-0.1.10.dist-info/WHEEL
dagorama-0.1.10.dist-info/entry_points.txt
dagorama-0.1.10.dist-info/RECORD
