Metadata-Version: 2.1
Name: dagorama
Version: 0.1.10
Summary: 
Author: Pierce Freeman
Author-email: pierce@freeman.vc
Requires-Python: >=3.10,<4.0
Classifier: Programming Language :: Python :: 3
Classifier: Programming Language :: Python :: 3.10
Classifier: Programming Language :: Python :: 3.11
Requires-Dist: click (>=8.1.3,<9.0.0)
Requires-Dist: grpcio (>=1.50.0,<2.0.0)
Requires-Dist: protobuf (>=4.21.9,<5.0.0)
Requires-Dist: watchdog (>=3.0.0,<4.0.0)
